brundle/__init__.py
brundle/brundle.py
brundle/py.typed
brundle-1.3.0.dist-info/LICENSE.txt
brundle-1.3.0.dist-info/METADATA
brundle-1.3.0.dist-info/WHEEL
brundle-1.3.0.dist-info/entry_points.txt
brundle-1.3.0.dist-info/top_level.txt
brundle-1.3.0.dist-info/RECORD
